vlppy/LICENSE.txt
vlppy/__init__.py
vlppy/__init__.pyi
vlppy/info.py
vlppy/info.pyi
vlppy/demo/README.md
vlppy/demo/__init__.py
vlppy/demo/demo_filter.py
vlppy/demo/demo_main.py
vlppy/demo/vlp_model.py
vlppy/error/__init__.py
vlppy/error/__init__.pyi
vlppy/error/error.py
vlppy/error/error.pyi
vlppy/io/__init__.py
vlppy/io/__init__.pyi
vlppy/io/io.py
vlppy/io/io.pyi
vlppy/model/__init__.py
vlppy/model/__init__.pyi
vlppy/model/led.py
vlppy/model/led.pyi
vlppy/model/pd.py
vlppy/model/pd.pyi
vlppy/model/pd2.py
vlppy/model/pd2.pyi
vlppy/model/room.py
vlppy/model/room.pyi
vlppy/setting/__init__.py
vlppy/setting/__init__.pyi
vlppy/setting/json_setting.py
vlppy/setting/json_setting.pyi
vlppy/setting/settings.json
vlppy/signal/__init__.py
vlppy/signal/__init__.pyi
vlppy/signal/filter.py
vlppy/signal/filter.pyi
vlppy/signal/plot.py
vlppy/signal/plot.pyi
vlppy/tools/__init__.py
vlppy/tools/__init__.pyi
vlppy/tools/decorator.py
vlppy/tools/decorator.pyi
vlppy/vis/__init__.py
vlppy/vis/__init__.pyi
vlppy/vis/vis.py
vlppy/vis/vis.pyi
vlppy-0.1.16.dist-info/LICENSE
vlppy-0.1.16.dist-info/METADATA
vlppy-0.1.16.dist-info/WHEEL
vlppy-0.1.16.dist-info/top_level.txt
vlppy-0.1.16.dist-info/RECORD
