Metadata-Version: 2.1
Name: vlppy
Version: 0.1.16
Summary: Construction of visible light positioning model
Home-page: https://gitee.com/yangwuju/vlppy.git
Author: yangwuju
Author-email: yangwuju <1424134319@qq.com>
License: Copyright (c) 2018 The Python Packaging Authority
Project-URL: Homepage, https://gitee.com/yangwuju/vlppy.git
Project-URL: Bug Tracker, https://gitee.com/yangwuju/vlppy/issues
Classifier: Programming Language :: Python :: 3
Classifier: License :: OSI Approved :: MIT License
Classifier: Operating System :: OS Independent
Requires-Python: >=3.5
License-File: LICENSE
